core/__init__.py
core/_data_loaders.py
core/_exceptions.py
core/_utils.py
core/schema.py
core/_converters/__init__.py
core/_converters/coco_converter.py
core/_converters/converter_factory.py
core/_converters/yolo_converter.py
core/_managers/base.py
core/_managers/metric_manager.py
core/_managers/plot_manager.py
core/_metrics/__init__.py
core/_metrics/common/auc.py
core/_metrics/common/average_precision.py
core/_metrics/common/blind_spot.py
core/_metrics/common/confidence_distribution.py
core/_metrics/common/confidence_distribution_histogram.py
core/_metrics/common/confusion_matrix.py
core/_metrics/common/dataset_population_distribution_age.py
core/_metrics/common/dataset_population_distribution_ethnicity.py
core/_metrics/common/dataset_population_distribution_gender.py
core/_metrics/common/dice.py
core/_metrics/common/dice_distribution.py
core/_metrics/common/iou.py
core/_metrics/common/iou_distribution.py
core/_metrics/common/lift_chart.py
core/_metrics/common/model_stats.py
core/_metrics/common/most_confused.py
core/_metrics/common/object_counts.py
core/_metrics/common/overall_metric.py
core/_metrics/common/predicted_distribution.py
core/_metrics/common/stats_tables.py
core/_metrics/common/threshold.py
core/_metrics/common/top_losses.py
core/_metrics/common/train_and_validation_performance.py
integrations/__init__.py
integrations/datasets/__init__.py
integrations/datasets/_download.py
integrations/datasets/_upload.py
integrations/datasets/api.py
integrations/validation/__init__.py
integrations/validation/_download.py
integrations/validation/api.py
validation/_result.py
validation/_validation.py
gesund-0.2.1.dist-info/LICENSE
gesund-0.2.1.dist-info/METADATA
gesund-0.2.1.dist-info/WHEEL
gesund-0.2.1.dist-info/top_level.txt
gesund-0.2.1.dist-info/RECORD
