Metadata-Version: 2.1
Name: gesund
Version: 0.2.1
Summary: A CRO platform for clinical-grade AI Train. Validate. Secure clearance. Gesund.ai orchestrates the AI as-a-Medical Device lifecycle, providing privacy-centered access to diverse yet standardized medical data sources, and a unique analytical toolbox that fosters clinical validation, regulatory clearance and effective marketing
Author-email: Veysel Koccaman <veysel@gesund.ai>, Hammad Khalid <hammad@gesund.ai>, Akson Varghese <akson@gesund.ai>, Ozkan Uysal <ozkan@gesund.ai>
Maintainer-email: Hammad Khalid <hammad@gesund.ai>, Akson Varghese <akson@gesund.ai>, Ozkan Uysal <ozkan@gesund.ai>
Project-URL: Homepage, https://github.com/gesund-ai/gesund
Project-URL: Issues, https://github.com/gesund-ai/gesund/issues
Project-URL: Documentation, https://gesund-ai.github.io/
Keywords: gesund,medical,radiology,machine learning,ai,artificial intelligence
Classifier: Programming Language :: Python :: 3
Classifier: License :: OSI Approved :: MIT License
Classifier: Operating System :: OS Independent
Requires-Python: >=3.6
License-File: LICENSE
Requires-Dist: docutils
Requires-Dist: requests
Requires-Dist: bson
Requires-Dist: jsonschema
Requires-Dist: scikit-learn
Requires-Dist: pandas
Requires-Dist: seaborn
Requires-Dist: opencv-python
Requires-Dist: dictances==1.5.3
Requires-Dist: miseval==1.2.2
Requires-Dist: numpy==1.21.6
Requires-Dist: numba==0.55.2
Requires-Dist: tqdm
Requires-Dist: pydantic==2.9.2
Provides-Extra: test
Requires-Dist: pytest; extra == "test"
Requires-Dist: pytest-cov; extra == "test"
